security77/__init__.py
security77/main.py
security77/passgen.py
security77-0.1.0.dist-info/entry_points.txt
security77-0.1.0.dist-info/LICENSE
security77-0.1.0.dist-info/WHEEL
security77-0.1.0.dist-info/METADATA
security77-0.1.0.dist-info/RECORD
