Metadata-Version: 2.1
Name: security77
Version: 0.1.0
Summary: A command-line tool and python package to make security simple.
Home-page: https://github.com/wallacesilva/security77/
License: MIT
Author: Wallace Silva
Author-email: contact@wallacesilva.com
Requires-Python: >=3.8,<4.0
Classifier: License :: OSI Approved :: MIT License
Classifier: Programming Language :: Python :: 3
Classifier: Programming Language :: Python :: 3.8
Requires-Dist: click (>=8.0.3,<9.0.0)
Project-URL: Documentation, https://github.com/wallacesilva/security77/
Project-URL: Repository, https://github.com/wallacesilva/security77/
